VectorMass/__init__.py
VectorMass/vector_store.py
VectorMass-0.0.1.dist-info/LICENSE
VectorMass-0.0.1.dist-info/METADATA
VectorMass-0.0.1.dist-info/WHEEL
VectorMass-0.0.1.dist-info/top_level.txt
VectorMass-0.0.1.dist-info/RECORD
