Metadata-Version: 2.1
Name: VectorMass
Version: 0.0.1
Summary: Highly flexible vector store
Home-page: https://github.com/dineshpiyasamara/VectorMass
Author: Dinesh Piyasamara
Author-email: dineshpiyasamara@gmail.com
License: MIT
Keywords: vector database,vector store
Classifier: License :: OSI Approved :: MIT License
Classifier: Development Status :: 1 - Planning
Classifier: Intended Audience :: Developers
Classifier: Programming Language :: Python :: 3
Classifier: Operating System :: Unix
Classifier: Operating System :: MacOS :: MacOS X
Classifier: Operating System :: Microsoft :: Windows
License-File: LICENSE
Requires-Dist: numpy
